illumigator/__init__.py
illumigator/entity.py
illumigator/geometry.py
illumigator/level.py
illumigator/level_selector.py
illumigator/light.py
illumigator/main.py
illumigator/menus.py
illumigator/object_animation.py
illumigator/util.py
illumigator/worldobjects.py
illumigator/assets/00_enemy_left.png
illumigator/assets/00_gator_left.png
illumigator/assets/00_gator_right.png
illumigator/assets/01_enemy_left.png
illumigator/assets/01_enemy_right.png
illumigator/assets/01_gator_left.png
illumigator/assets/01_gator_right.png
illumigator/assets/02_enemy_left.png
illumigator/assets/02_enemy_right.png
illumigator/assets/02_gator_left.png
illumigator/assets/02_gator_right.png
illumigator/assets/03_enemy_left.png
illumigator/assets/03_enemy_right.png
illumigator/assets/03_gator_left.png
illumigator/assets/03_gator_right.png
illumigator/assets/04_enemy_left.png
illumigator/assets/04_enemy_right.png
illumigator/assets/04_gator_left.png
illumigator/assets/04_gator_right.png
illumigator/assets/05_gator_left.png
illumigator/assets/05_gator_right.png
illumigator/assets/06_gator_left.png
illumigator/assets/06_gator_right.png
illumigator/assets/07_gator_left.png
illumigator/assets/07_gator_right.png
illumigator/assets/08_gator_left.png
illumigator/assets/08_gator_right.png
illumigator/assets/09_gator_left.png
illumigator/assets/09_gator_right.png
illumigator/assets/FLman_run_right3.png
illumigator/assets/FLman_running_left0.png
illumigator/assets/FLman_running_left1.png
illumigator/assets/FLman_running_left2.png
illumigator/assets/FLman_running_left3.png
illumigator/assets/FLman_running_left4.png
illumigator/assets/FLman_running_right0.png
illumigator/assets/FLman_running_right1.png
illumigator/assets/FLman_running_right2.png
illumigator/assets/FLman_running_right3.png
illumigator/assets/FLman_running_right4.png
illumigator/assets/FLman_sleeping0.png
illumigator/assets/FLman_sleeping1.png
illumigator/assets/Gator_death_left0.png
illumigator/assets/Gator_death_left1.png
illumigator-0.0.15.dist-info/METADATA
illumigator-0.0.15.dist-info/WHEEL
illumigator-0.0.15.dist-info/entry_points.txt
illumigator-0.0.15.dist-info/licenses/LICENSE
illumigator-0.0.15.dist-info/RECORD
