Metadata-Version: 2.1
Name: illumigator
Version: 0.0.15
Summary: 2D Light-Based Puzzle Game
Project-URL: Homepage, https://github.com/EltonLi2000/IllumiGator
Project-URL: Bug Tracker, https://github.com/EltonLi2000/IllumiGator/issues
Author-email: Richard Sorkin <r.sorkin@ufl.edu>, Tomas Mejia <tomas.mejia@ufl.edu>, Amber Handal <amberhandal@ufl.edu>, Elton Li <eltonli@ufl.edu>, Dakota Cappel <dakota.cappel@ufl.edu>
License-File: LICENSE
Classifier: License :: OSI Approved :: MIT License
Classifier: Operating System :: OS Independent
Classifier: Programming Language :: Python :: 3
Requires-Python: >=3.10
Requires-Dist: arcade
Requires-Dist: numpy
Requires-Dist: pydantic
Requires-Dist: screeninfo
